MANIFEST.in
setup.cfg
setup.py
tictactoe_learn/__init__.py
tictactoe_learn/__main__.py
tictactoe_learn.egg-info/PKG-INFO
tictactoe_learn.egg-info/SOURCES.txt
tictactoe_learn.egg-info/dependency_links.txt
tictactoe_learn.egg-info/requires.txt
tictactoe_learn.egg-info/top_level.txt