Metadata-Version: 1.1
Name: tictactoe-learn
Version: 0.0.1
Summary: A learning program that plays with the users and depends on their inputs to learn optimal strategy in the classic game of tic-tac-toe.
Home-page: https://github.com/Avikalp7/TicTacToe-Reinforcement-Learning
Author: Avikalp Srivastava
Author-email: avikalp22@iitkgp.ac.in
License: MIT
Keywords: IIT,KGP,Tic Tac Toe,Tic Tac,Avikalp Srivastava,CG Accumulator,Python,Reinforcement Learning,Machine Learning
Platform: UNKNOWN
Classifier: Development Status :: 3 - Alpha
Classifier: Intended Audience :: End Users/Desktop
Classifier: License :: OSI Approved :: MIT License
Classifier: Programming Language :: Python :: 2.7
